findl/__init__.py
findl/findl.py
findl/weblib/__init__.py
findl/weblib/nse.py
findl-1.0.2.dist-info/DESCRIPTION.rst
findl-1.0.2.dist-info/METADATA
findl-1.0.2.dist-info/RECORD
findl-1.0.2.dist-info/WHEEL
findl-1.0.2.dist-info/metadata.json
findl-1.0.2.dist-info/top_level.txt
